{
    "exercises": [
      {
        "name": "model::test_load_safetensors",
        "result": false
      },
      {
        "name": "model::test_mlp",
        "result": false
      },
      {
        "name": "operators::test_matmul_transb",
        "result": false
      },
      {
        "name": "operators::test_rms_norm",
        "result": false
      },
      {
        "name": "operators::test_silu",
        "result": false
      }
    ],
    "user_name": null,
    "statistics": {
      "total_exercations": 5,
      "total_succeeds": 0,
      "total_failures": 5,
      "total_time": 3
    }
  }